CHANGES.txt
README.txt
setup.cfg
setup.py
js/__init__.py
js/__init__.pyc
js.jquery_infinite_ajax_scroll.egg-info/PKG-INFO
js.jquery_infinite_ajax_scroll.egg-info/SOURCES.txt
js.jquery_infinite_ajax_scroll.egg-info/dependency_links.txt
js.jquery_infinite_ajax_scroll.egg-info/entry_points.txt
js.jquery_infinite_ajax_scroll.egg-info/namespace_packages.txt
js.jquery_infinite_ajax_scroll.egg-info/not-zip-safe
js.jquery_infinite_ajax_scroll.egg-info/requires.txt
js.jquery_infinite_ajax_scroll.egg-info/top_level.txt
js/jquery_infinite_ajax_scroll/__init__.py
js/jquery_infinite_ajax_scroll/__init__.pyc
js/jquery_infinite_ajax_scroll/test_jquery_infinite_ajax_scroll.txt
js/jquery_infinite_ajax_scroll/resources/CHANGELOG.textile
js/jquery_infinite_ajax_scroll/resources/MIT-LICENSE.txt
js/jquery_infinite_ajax_scroll/resources/README.textile
js/jquery_infinite_ajax_scroll/resources/jquery.ias.js
js/jquery_infinite_ajax_scroll/resources/jquery.ias.min.js
js/jquery_infinite_ajax_scroll/resources/css/jquery.ias.css
js/jquery_infinite_ajax_scroll/resources/images/loader.gif