Metadata-Version: 1.0
Name: js.jquery-infinite-ajax-scroll
Version: 0.1
Summary: fanstatic jquery infinite ajax scroll
Home-page: UNKNOWN
Author: Marco Scheidhuber
Author-email: j23d@jusid.de
License: MIT
Keywords: fanstatic infinit-ajax-scroll
Platform: UNKNOWN
